load_dataset
setup.py
start_parquet2hive_server
parquet2hive_server/__init__.py
parquet2hive_server/client.py
parquet2hive_server/server.py
parquet2hive_server/settings.py
parquet2hive_server.egg-info/PKG-INFO
parquet2hive_server.egg-info/SOURCES.txt
parquet2hive_server.egg-info/dependency_links.txt
parquet2hive_server.egg-info/requires.txt
parquet2hive_server.egg-info/top_level.txt