Metadata-Version: 1.0
Name: parquet2hive-server
Version: 0.0.4
Summary: API Endpoint for Parquet2hive
Home-page: https://github.com/fbertsch/parquet2hive_server
Author: Frank Bertsch
Author-email: fbertsch@mozilla.com
License: UNKNOWN
Platform: UNKNOWN
